[{"registeredDate":"9월 23, 2021","viewCount":0,"like":0,"no":1,"writer":{"userAccessLevel":2,"name":"user2","id":"2@test.com","password":"!12345678","phoneNumber":"01012345678","registeredDate":"9월 23, 2021"},"title":"user2의 스몰톡 게시글","content":"user2의 스몰톡 게시글"},{"registeredDate":"9월 23, 2021","viewCount":0,"like":0,"no":2,"writer":{"userAccessLevel":2,"name":"user3","id":"3@test.com","password":"!12345678","phoneNumber":"01011111111","registeredDate":"9월 23, 2021"},"title":"user3의 스몰톡 게시글","content":"user3의 스몰톡 게시글"}]